Proyecto/src/design/module_debounce.sv
module debounce #(parameter N = 21 )
(
 //Entradas
    input logic clk,  //reloj
    input logic rst, //reset
    input logic valido, //señal del teclado
    input logic [3:0] tecla, //valor de la tecla


 //Salidas
    output logic limpio, // pulso cunado una tecla es válida
    output logic [3:0] seleccion // valor de la tecla valida
);


logic DFF1, DFF2; // Son 2 flip-flops 


// Esto ejecuta cuando en cada subida del relo o cuando hay un reset
always_ff @(posedge clk or posedge rst) begin
    if (rst) begin  //Si hay reset, es cero
        DFF1 <= 0;
        DFF2 <= 0;
    end else begin
       DFF1 <= valido; // guarda valido
       DFF2 <= DFF1; // guarde el valor anterior de DFF1 (DDF2 es una versión estable y sincronizada de la señal)
    end
    
end


logic [N-1:0] q_reg, q_next; // q_reg: valor actual del contador. q_next: es el siguiente valor.

wire q_reset; //reinicia el contador
wire q_add; // inidca si debe seguir contando



assign q_reset = (DFF1 ^ DFF2); // La XOR detecta cambios, si la señal cambia, es 1 y si es estable es 0. Si hay rebote, se reinicia el contador.

assign q_add = ~q_reg[N-1]; // Mientras el bit significativo sea 0, va seguir contando y cuando sea 1, deja de contar


//Logica combinacional del contador (sin memoria)
always_comb begin 
     if (q_reset) // Si hay rebote, reinicia el contador
        q_next = '0;
    else if (q_add) // Si no hay robote, suma 1
        q_next = q_reg + 1;
    else // Si llega al máximo, se queda igual.
        q_next = q_reg;
  
end

//Registro del contador
always_ff @(posedge clk or posedge rst) begin
    if (rst)
    q_reg <= '0; // si se resetea, el contador es 0
    else
    q_reg <= q_next; // guarda el siguiente valor
    
end

logic valido_limpio; //Señal ya filtrada

always_ff @(posedge clk or posedge rst) begin
 if (rst) // si se resetea, el valor_limpio es 0
        valido_limpio <= 0;
    else if (q_reg[N-1]) //Si el contador llegó al máximo, la señal ya es estable y se acepta como válida
        valido_limpio <= DFF2;
    else
        valido_limpio <= valido_limpio; // Se mantiene el valor anterior
end
// Detecta si está limpio

logic valido_prev; //guarda el valor anterior

always_ff @(posedge clk or posedge rst) begin
if(rst) // si se resetea, el valor_prev es 0
valido_prev <=0;
else
valido_prev <= valido_limpio; //Se actualiza
end

assign limpio = valido_limpio & ~valido_prev; // Esto detecta cuando pasa de 0 a 1 y genera un pulos de 1 ciclo de reloj


logic [3:0] tecla_sync; //Se registra la tecla

always_ff @(posedge clk or posedge rst) begin
    if (rst)
        tecla_sync <= 0;
    else
        tecla_sync <= tecla; // Copia la tecla al reloj
end



always_ff @(posedge clk or posedge rst) begin // Bloque secuencial
    if(rst) // Si hay reseteo, no hay tecla
    seleccion <=0;
    else if(limpio) //Guarda la tecla si está valida
    seleccion <= tecla_sync;
end


endmodule

Proyecto/src/sim/module_debounce_tb.sv
`timescale 1 ns / 100 ps

module debounce_tb;

logic clk;
logic rst;
logic valido;
logic [3:0] tecla;

wire limpio;
wire [3:0] seleccion;

debounce #(.N(4)) UUT(
    .clk(clk),
    .rst(rst),
    .valido(valido),
    .tecla(tecla),
    .limpio(limpio),
    .seleccion(seleccion)
);

initial begin
    clk = 0;
    rst = 1;
    valido = 0;
    tecla = 4'd0;

    #100 rst = 0;

end

always #10 clk = ~clk; // Un period de 20 ns

initial begin

   #200;

    
    tecla = 4'd5; //Se presiona la tecla 5

    //Simulación de rebote
    #50  valido = 1;
    #20  valido = 0;
    #20  valido = 1;
    #20  valido = 0;
    #20  valido = 1;

    
    #30000 valido = 1; //Mantiene la señal estable

    
    #2000 valido = 0;

    
    #2000;
    tecla = 4'd7; //Se presiona otra tecla (7) y el mismo proceso.

    // Simula un rebote
    #50  valido = 1;
    #20  valido = 0;
    #20  valido = 1;

    
    #30000 valido = 1;

    
    #2000 valido = 0;

    
    #1000;
    tecla = 4'd3;

    #20 valido = 1;
    #20 valido = 0;
    #20 valido = 1;
    #20 valido = 0;

    #200 valido = 1; 


   

    #30000;

    $finish;
end 
initial begin
        $dumpfile("top_tb.vcd");
        $dumpvars(0,debounce_tb);
    end


    

endmodule

Proyecto/src/build/top_tb.vcd
$date
	Sat May 02 16:12:21 2026
$end
$version
	Icarus Verilog
$end
$timescale
	100ps
$end
$scope module debounce_tb $end
$var wire 4 ! seleccion [3:0] $end
$var wire 1 " limpio $end
$var reg 1 # clk $end
$var reg 1 $ rst $end
$var reg 4 % tecla [3:0] $end
$var reg 1 & valido $end
$scope module UUT $end
$var wire 1 # clk $end
$var wire 1 " limpio $end
$var wire 1 ' q_add $end
$var wire 1 ( q_reset $end
$var wire 1 $ rst $end
$var wire 4 ) tecla [3:0] $end
$var wire 1 & valido $end
$var parameter 32 * N $end
$var reg 1 + DFF1 $end
$var reg 1 , DFF2 $end
$var reg 4 - q_next [3:0] $end
$var reg 4 . q_reg [3:0] $end
$var reg 4 / seleccion [3:0] $end
$var reg 4 0 tecla_sync [3:0] $end
$var reg 1 1 valido_limpio $end
$var reg 1 2 valido_prev $end
$upscope $end
$upscope $end
$enddefinitions $end
$comment Show the parameter values. $end
$dumpall
b100 *
$end
#0
$dumpvars
02
01
b0 0
b0 /
b0 .
b1 -
0,
0+
b0 )
0(
1'
0&
b0 %
1$
0#
0"
b0 !
$end
#100
1#
#200
0#
#300
1#
#400
0#
#500
1#
#600
0#
#700
1#
#800
0#
#900
1#
#1000
0#
0$
#1100
b10 -
b1 .
1#
#1200
0#
#1300
b11 -
b10 .
1#
#1400
0#
#1500
b100 -
b11 .
1#
#1600
0#
#1700
b101 -
b100 .
1#
#1800
0#
#1900
b110 -
b101 .
1#
#2000
0#
b101 %
b101 )
#2100
b111 -
b101 0
b110 .
1#
#2200
0#
#2300
b1000 -
b111 .
1#
#2400
0#
#2500
0'
b0 -
1(
b1000 .
1+
1#
1&
#2600
0#
#2700
1'
1,
0+
b0 .
1#
0&
#2800
0#
#2900
0,
1+
1#
1&
#3000
0#
#3100
1,
0+
1#
0&
#3200
0#
#3300
0,
1+
1#
1&
#3400
0#
#3500
b1 -
0(
1,
1#
#3600
0#
#3700
b10 -
b1 .
1#
#3800
0#
#3900
b11 -
b10 .
1#
#4000
0#
#4100
b100 -
b11 .
1#
#4200
0#
#4300
b101 -
b100 .
1#
#4400
0#
#4500
b110 -
b101 .
1#
#4600
0#
#4700
b111 -
b110 .
1#
#4800
0#
#4900
b1000 -
b111 .
1#
#5000
0#
#5100
0'
b1000 -
b1000 .
1#
#5200
0#
#5300
1"
11
1#
#5400
0#
#5500
0"
12
b101 !
b101 /
1#
